Deep_Learning_Framework/Activation.py
Deep_Learning_Framework/Evaluation.py
Deep_Learning_Framework/Load.py
Deep_Learning_Framework/activations.py
Deep_Learning_Framework/boda.py
Deep_Learning_Framework/layer.py
Deep_Learning_Framework/loss.py
Deep_Learning_Framework/main.py
Deep_Learning_Framework/model.py
Deep_Learning_Framework/save_and_load.py
Deep_Learning_Framework/setup.py
Deep_Learning_Framework/utils.py
Deep_Learning_Framework/visualization.py
BasicDeepLearningFramework-0.3.0.dist-info/LICENSE.txt
BasicDeepLearningFramework-0.3.0.dist-info/METADATA
BasicDeepLearningFramework-0.3.0.dist-info/WHEEL
BasicDeepLearningFramework-0.3.0.dist-info/top_level.txt
BasicDeepLearningFramework-0.3.0.dist-info/RECORD
