Metadata-Version: 2.1
Name: BasicDeepLearningFramework
Version: 0.3.0
Summary: A Deep learning framework can be used to build deep learning models and CNNS
Home-page: UNKNOWN
Author: Omar Hatem
Author-email: omarhatem221@gmail.com
License: MIT
Keywords: deep learning framework
Platform: UNKNOWN
Classifier: Development Status :: 5 - Production/Stable
Classifier: Intended Audience :: Education
Classifier: Operating System :: Microsoft :: Windows :: Windows 10
Classifier: License :: OSI Approved :: MIT License
Classifier: Programming Language :: Python :: 3
Requires-Dist: numpy
Requires-Dist: pandas
Requires-Dist: matplotlib
Requires-Dist: Pillow
